{
  "name": "PATCH /ideas/status",
  "nodes": [
    {
      "parameters": {
        "httpMethod": "PATCH",
        "path": "ideas/:id/status",
        "responseMode": "responseNode",
        "options": { "allowedOrigins": "*" }
      },
      "id": "04bdc1ad-f780-4696-88fa-9b049cd000f7",
      "name": "Webhook",
      "type": "n8n-nodes-base.webhook",
      "typeVersion": 2,
      "position": [240, 300],
      "webhookId": "1929d2e1-4659-473c-973d-49397b9be849"
    },
    {
      "parameters": {
        "mode": "runOnceForEachItem",
        "jsCode": "const CONFIG = {\n  AIRTABLE_PAT: $env.AIRTABLE_PAT || $env.AIRTABLE_API_KEY || \"\",\n  AIRTABLE_BASE_ID: $env.AIRTABLE_BASE_ID || \"\",\n  SHARED_API_KEY: $env.SHARED_API_KEY || \"\",\n  IDEAS_TABLE: $env.AIRTABLE_IDEAS_TABLE || \"Ideas\",\n};\n\nconst headersIn = $json.headers || {};\n\nif (String(headersIn[\"x-api-key\"] || \"\") !== CONFIG.SHARED_API_KEY) {\n  return { json: { statusCode: 401, body: { error: \"unauthorized\", code: \"no_key\" } } };\n}\nconst sessionToken = String(headersIn[\"x-session-token\"] || \"\").trim();\nif (!sessionToken) {\n  return { json: { statusCode: 401, body: { error: \"Session required\", code: \"session_missing\" } } };\n}\nif (!CONFIG.AIRTABLE_PAT || !CONFIG.AIRTABLE_BASE_ID) {\n  return { json: { statusCode: 500, body: { error: \"Airtable config missing\", code: \"airtable_config_missing\" } } };\n}\n\nconst request = this.helpers.httpRequest.bind(this.helpers);\nconst airtable = \"https://api.airtable.com/v0/\" + CONFIG.AIRTABLE_BASE_ID;\nconst headers = { Authorization: \"Bearer \" + CONFIG.AIRTABLE_PAT };\n\nconst ideaId = String($json.params?.id || \"\").trim();\nconst bodyIn = $json.body || {};\nconst status = String(bodyIn.status || \"\").trim();\nconst userId = String(headersIn[\"x-user-id\"] || \"\").trim();\n\nconst VALID_STATUSES = [\"voting\", \"selected\", \"scheduled\", \"done\"];\nif (!VALID_STATUSES.includes(status)) {\n  return { json: { statusCode: 400, body: { error: \"Statut invalide\", code: \"invalid_status\" } } };\n}\nif (!ideaId) {\n  return { json: { statusCode: 400, body: { error: \"ID idée manquant\", code: \"idea_id_missing\" } } };\n}\n\n// Lookup by custom {id} field (e.g. idea_recXXX)\nconst esc = (v) => String(v || \"\").replace(/'/g, \"\\\\'\");\nconst formula = \"{id} = '\" + esc(ideaId) + \"'\";\nlet ideaRecord;\ntry {\n  const data = await request({\n    method: \"GET\",\n    url: airtable + \"/\" + encodeURIComponent(CONFIG.IDEAS_TABLE) + \"?maxRecords=1&filterByFormula=\" + encodeURIComponent(formula),\n    headers,\n    json: true,\n  });\n  ideaRecord = data.records?.[0];\n} catch (e) {\n  return { json: { statusCode: 500, body: { error: \"Airtable error: \" + (e?.message || String(e)), code: \"airtable_lookup_failed\" } } };\n}\n\nif (!ideaRecord) {\n  return { json: { statusCode: 404, body: { error: \"Idée introuvable\", code: \"idea_not_found\" } } };\n}\n\nconst f = ideaRecord.fields || {};\n\nlet updated;\ntry {\n  updated = await request({\n    method: \"PATCH\",\n    url: airtable + \"/\" + encodeURIComponent(CONFIG.IDEAS_TABLE) + \"/\" + ideaRecord.id,\n    headers,\n    body: { fields: { status } },\n    json: true,\n  });\n} catch (e) {\n  return { json: { statusCode: 500, body: { error: \"Airtable error: \" + (e?.message || String(e)), code: \"airtable_update_failed\" } } };\n}\n\nconst uf = updated.fields || {};\nlet likes = [];\nlet dislikes = [];\ntry { likes = JSON.parse(f.likes || \"[]\"); } catch { likes = []; }\ntry { dislikes = JSON.parse(f.dislikes || \"[]\"); } catch { dislikes = []; }\nif (!Array.isArray(likes)) likes = [];\nif (!Array.isArray(dislikes)) dislikes = [];\n\nconst myVote = userId\n  ? (likes.includes(userId) ? \"like\" : dislikes.includes(userId) ? \"dislike\" : null)\n  : null;\n\nreturn {\n  json: {\n    statusCode: 200,\n    body: {\n      idea: {\n        id: String(uf.id || f.id || updated.id),\n        title: String(uf.title || f.title || \"\"),\n        description: String(uf.description || f.description || \"\"),\n        proposed_by_id: String(uf.proposed_by || f.proposed_by || \"\"),\n        proposed_by_name: String(uf.proposed_by_name || f.proposed_by_name || uf.proposed_by || f.proposed_by || \"\"),\n        status,\n        likes,\n        dislikes,\n        my_vote: myVote,\n      },\n    },\n  },\n};"
      },
      "id": "a7b8c9d0-e1f2-3456-abcd-567890123456",
      "name": "Set Idea Status",
      "type": "n8n-nodes-base.code",
      "typeVersion": 2,
      "position": [480, 300]
    },
    {
      "parameters": {
        "respondWith": "json",
        "responseBody": "={{ JSON.stringify($json.body) }}",
        "options": {
          "responseCode": "={{ $json.statusCode || 200 }}"
        }
      },
      "id": "b8c9d0e1-f2a3-4567-bcde-678901234567",
      "name": "Respond",
      "type": "n8n-nodes-base.respondToWebhook",
      "typeVersion": 1.2,
      "position": [720, 300]
    }
  ],
  "connections": {
    "Webhook": {
      "main": [[{ "node": "Set Idea Status", "type": "main", "index": 0 }]]
    },
    "Set Idea Status": {
      "main": [[{ "node": "Respond", "type": "main", "index": 0 }]]
    }
  },
  "pinData": {},
  "settings": { "executionOrder": "v1" },
  "active": false,
  "meta": { "templateCredsSetupCompleted": false }
}
